aleo-0.1.0.dist-info/METADATA
aleo-0.1.0.dist-info/WHEEL
aleo/__init__.py
aleo/aleo.cpython-311-darwin.so
aleo-0.1.0.dist-info/RECORD
