Metadata-Version: 2.1
Name: aleo
Version: 0.1.0
Summary: A Python sdk for zero-knowledge cryptography based on Aleo
Author: Konstantin Pandl, Mike Turner, Roman Proskuryakov
License: GPL-3.0-or-later
